Metadata-Version: 2.1
Name: lshcos
Version: 0.0.2
Summary: A fast Python implementation of locality sensitive hashing with cosine distance.
Home-page: https://github.com/jinzitian/LSHCos
Author: Chef_J
Author-email: hedge_jzt@hotmail.com
Maintainer: Chef_J
Maintainer-email: hedge_jzt@hotmail.com
License: MIT
Platform: UNKNOWN
Classifier: Intended Audience :: Developers
Classifier: License :: OSI Approved :: MIT License
Classifier: Operating System :: OS Independent
Classifier: Programming Language :: Python
Classifier: Programming Language :: Python :: 3
Classifier: Topic :: Software Development :: Libraries
